secfn/__init__.py
secfn/schema.py
secfn/secfn.py
secfn/types.py
secfn/access_control/__init__.py
secfn/access_control/rbac.py
secfn/monitoring/__init__.py
secfn/monitoring/security_monitor.py
secfn/rate_limiting/__init__.py
secfn/rate_limiting/rate_limiter.py
secfn/scanning/__init__.py
secfn/scanning/patterns.py
secfn/scanning/scanner.py
secfn/secrets/__init__.py
secfn/secrets/encryption.py
secfn/secrets/vault.py
secfn/storage/__init__.py
secfn/storage/file_storage.py
secfn/utils/__init__.py
secfn/utils/helpers.py
secfn-0.0.1.dist-info/METADATA
secfn-0.0.1.dist-info/WHEEL
secfn-0.0.1.dist-info/RECORD
